[{
  "_id": {
    "$oid": "5f0d631c0039e729c01c2bbc"
  },
  "comment": "It's got me back into my running. Lockdown has helped me find my fitness again. Plus it really helps clear my head.",
  "postId": "5f0d62280039e729c01c2bbb",
  "user": "pete",
  "createdAt": {
    "$date": "2020-07-14T07:47:40.983Z"
  },
  "updatedAt": {
    "$date": "2020-07-14T07:47:40.983Z"
  },
  "__v": 0
},{
  "_id": {
    "$oid": "5f0d9151f121923b5c0ee9c8"
  },
  "comment": "Can't wait. Hope Owen brings some of his beetroot chutney.",
  "postId": "5f0d63a70039e729c01c2bbd",
  "user": "dave",
  "createdAt": {
    "$date": "2020-07-14T11:04:49.587Z"
  },
  "updatedAt": {
    "$date": "2020-07-14T11:04:49.587Z"
  },
  "__v": 0
}]